{
  "worlds": {
    "1": {
      "goal_found": true,
      "goal_reward": 1.0,
      "hazards_found": 7,
      "goal_hits_completed": 3,
      "optimization_runs_completed": 0,
      "terminals_found": 49,
      "last_terminal_kind": "goal",
      "last_terminal_reward": 10000.0,
      "last_known_state": null
    },
    "2": {
      "goal_found": true,
      "goal_reward": 1000.0,
      "hazards_found": 0,
      "goal_hits_completed": 5,
      "optimization_runs_completed": 0,
      "terminals_found": 21,
      "last_terminal_kind": "goal",
      "last_terminal_reward": 1000.0,
      "last_known_state": null
    },
    "3": {
      "goal_found": true,
      "goal_reward": 0.0,
      "hazards_found": 0,
      "goal_hits_completed": 5,
      "optimization_runs_completed": 0,
      "terminals_found": 0,
      "last_terminal_kind": null,
      "last_terminal_reward": null,
      "last_known_state": null
    },
    "4": {
      "goal_found": true,
      "goal_reward": 100000.0,
      "hazards_found": 0,
      "goal_hits_completed": 5,
      "optimization_runs_completed": 0,
      "terminals_found": 25,
      "last_terminal_kind": "goal",
      "last_terminal_reward": 100000.0,
      "last_known_state": null
    },
    "5": {
      "goal_found": false,
      "goal_reward": null,
      "hazards_found": 3,
      "goal_hits_completed": 0,
      "optimization_runs_completed": 0,
      "terminals_found": 6,
      "last_terminal_kind": "hazard",
      "last_terminal_reward": -100000.0,
      "last_known_state": null
    },
    "6": {
      "goal_found": false,
      "goal_reward": null,
      "hazards_found": 0,
      "goal_hits_completed": 0,
      "optimization_runs_completed": 0,
      "terminals_found": 0,
      "last_terminal_kind": null,
      "last_terminal_reward": null,
      "last_known_state": null
    },
    "7": {
      "goal_found": false,
      "goal_reward": null,
      "hazards_found": 0,
      "goal_hits_completed": 0,
      "optimization_runs_completed": 0,
      "terminals_found": 0,
      "last_terminal_kind": null,
      "last_terminal_reward": null,
      "last_known_state": null
    },
    "8": {
      "goal_found": false,
      "goal_reward": null,
      "hazards_found": 0,
      "goal_hits_completed": 0,
      "optimization_runs_completed": 0,
      "terminals_found": 0,
      "last_terminal_kind": null,
      "last_terminal_reward": null,
      "last_known_state": null
    },
    "9": {
      "goal_found": false,
      "goal_reward": null,
      "hazards_found": 0,
      "goal_hits_completed": 0,
      "optimization_runs_completed": 0,
      "terminals_found": 0,
      "last_terminal_kind": null,
      "last_terminal_reward": null,
      "last_known_state": null
    },
    "10": {
      "goal_found": false,
      "goal_reward": null,
      "hazards_found": 0,
      "goal_hits_completed": 0,
      "optimization_runs_completed": 0,
      "terminals_found": 0,
      "last_terminal_kind": null,
      "last_terminal_reward": null,
      "last_known_state": null
    }
  },
  "active_world": 5,
  "last_enter_ts": 1777525845.7351985,
  "last_summary": {
    "world_id": 5,
    "terminal_attempt": 6,
    "episode": 6,
    "total_reward": -100369.0,
    "total_policy_reward": -300390.5,
    "steps": 370,
    "ended": true,
    "epsilon_after": 0.2940367562499999,
    "unique_states": 175,
    "blocked_moves": 0,
    "invalid_moves": 0,
    "assumed_terminal_events": 1,
    "mean_abs_td_error": 811.8457937637445,
    "terminal_reward": -100000.0,
    "terminal_kind": "hazard",
    "ended_by_step_limit": false,
    "final_state": null,
    "action_counts": {
      "N": 113,
      "S": 82,
      "E": 104,
      "W": 71
    },
    "timestamp": "2026-04-30 09:10:43"
  },
  "campaign_world_start": 1,
  "campaign_world_end": 10,
  "traversals_per_world": 5
}